ha_lights/__init__.py
ha_lights/ha_lights.py
home_assistant_lights-0.0.5.post1.dist-info/METADATA
home_assistant_lights-0.0.5.post1.dist-info/WHEEL
home_assistant_lights-0.0.5.post1.dist-info/top_level.txt
home_assistant_lights-0.0.5.post1.dist-info/RECORD
