Metadata-Version: 2.1
Name: home-assistant-lights
Version: 0.0.5.post1
Summary: Simple python library to control lights and switches in Home Assistant..
Home-page: https://github.com/maximehk/ha_lights
Author: Maxime
Author-email: 
Classifier: Programming Language :: Python :: 3
Classifier: License :: OSI Approved :: MIT License
Classifier: Operating System :: OS Independent
Requires-Python: >=3.6
Requires-Dist: homeassistant-api (>=4.0.0.post2)
